[
	{
		"repo": "soup-bowl/whatsth.is",
		"image": "https://f.subo.dev/i/r/wt.webp"
	},
	{
		"repo": "soup-bowl/pressify",
		"image": "https://f.subo.dev/i/r/press.webp"
	},
	{
		"repo": "soup-bowl/Modoki-Firefox",
		"image": "https://f.subo.dev/i/r/mm.webp"
	},
	{
		"repo": "soup-bowl/simple-smtp",
		"image": "https://f.subo.dev/i/r/wpss.webp"
	},
	{
		"repo": "soup-bowl/soup-bowl.github.io",
		"image": "https://f.subo.dev/i/r/sb.webp"
	},
	{
		"repo": "soup-bowl/labs",
		"image": "https://f.subo.dev/i/r/lab.webp"
	},
	{
		"repo": "soup-bowl/chromeboard",
		"image": "https://f.subo.dev/i/r/cb.webp"
	},
	{
		"repo": "soup-bowl/opensimulator-docker",
		"image": "https://f.subo.dev/i/r/os.webp"
	},
	{
		"repo": "soup-bowl/opensim-sandbox",
		"image": "https://f.subo.dev/i/r/os.webp"
	},
	{
		"repo": "soup-bowl/deskdash",
		"image": "https://f.subo.dev/i/r/dd.webp"
	},
	{
		"repo": "soup-bowl/hot-this-week",
		"image": "https://f.subo.dev/i/r/htw.webp"
	}
]
